vcdextproxy/__init__.py
vcdextproxy/__main__.py
vcdextproxy/amqp_worker.py
vcdextproxy/api_extension.py
vcdextproxy/configuration.py
vcdextproxy/rest_worker.py
vcdextproxy/utils.py
vcdextproxy/vcd_utils.py
vcdextproxy-0.1.1.dist-info/AUTHORS.rst
vcdextproxy-0.1.1.dist-info/LICENSE
vcdextproxy-0.1.1.dist-info/METADATA
vcdextproxy-0.1.1.dist-info/WHEEL
vcdextproxy-0.1.1.dist-info/entry_points.txt
vcdextproxy-0.1.1.dist-info/top_level.txt
vcdextproxy-0.1.1.dist-info/RECORD
