Metadata-Version: 2.1
Name: vcdextproxy
Version: 0.1.1
Summary: A python based proxy looking at multiple AMQP queues for incoming requests of VMware vCloud Director's API Extensions
Home-page: https://github.com/lrivallain/vcdextproxy
Author: Ludovic Rivallain
Author-email: ludovic.rivallain@gmail.com
License: MIT license
Keywords: vcdextproxy
Platform: UNKNOWN
Classifier: Development Status :: 2 - Pre-Alpha
Classifier: Intended Audience :: Developers
Classifier: License :: OSI Approved :: MIT License
Classifier: Natural Language :: English
Classifier: Programming Language :: Python :: 3.6
Classifier: Programming Language :: Python :: 3.7
Classifier: Programming Language :: Python :: 3.8
Requires-Python: >=3.6
Requires-Dist: kombu
Requires-Dist: coloredlogs
Requires-Dist: requests
Requires-Dist: cachetools
Requires-Dist: PyYAML
